SqlDataApi/SqlDataApi.py
SqlDataApi/__init__.py
sql_data_api_client-0.1.4.dist-info/LICENSE
sql_data_api_client-0.1.4.dist-info/METADATA
sql_data_api_client-0.1.4.dist-info/WHEEL
sql_data_api_client-0.1.4.dist-info/top_level.txt
sql_data_api_client-0.1.4.dist-info/RECORD
