Metadata-Version: 2.1
Name: sql-data-api-client
Version: 0.1.4
Summary: Python library for Sql Data Api
Home-page: https://github.com/FalconSoft/sql-data-api-client-Python
Author: FalconSoft Ltd
Author-email: ppaska@falconsoft-ltd.com
License: UNKNOWN
Platform: UNKNOWN
Classifier: Programming Language :: Python :: 3
Classifier: License :: OSI Approved :: MIT License
Classifier: Operating System :: OS Independent
Requires-Python: >=3.6
